PAModelpy/CatalyticEvent.py
PAModelpy/Constraints.py
PAModelpy/Enzyme.py
PAModelpy/EnzymeSectors.py
PAModelpy/PAMValidator.py
PAModelpy/PAModel.py
PAModelpy/__init__.py
PAModelpy/configuration.py
PAModelpy/flux_analysis/__init__.py
PAModelpy/flux_analysis/flux_variability_analysis.py
PAModelpy/utils/__init__.py
PAModelpy/utils/pam_generation.py
PAModelpy/utils/recombinant_protein_expression.py
PAModelpy/utils/visualize_protein_sectors.py
pamodelpy-0.0.5.2.dist-info/METADATA
pamodelpy-0.0.5.2.dist-info/WHEEL
pamodelpy-0.0.5.2.dist-info/top_level.txt
pamodelpy-0.0.5.2.dist-info/RECORD
