Metadata-Version: 2.4
Name: PAModelpy
Version: 0.0.5.2
Summary: Python framework for building and analysing protein allocation models
Author-email: Samira van den Bogaard <samira.vandenbogaard@rwth-aachen.de>
Classifier: Programming Language :: Python :: 3
Classifier: License :: OSI Approved :: MIT License
Classifier: Operating System :: OS Independent
Requires-Python: <3.12,>=3.9
Requires-Dist: cobra==0.29.0
Requires-Dist: openpyxl~=3.1
Requires-Dist: numpy<1.26,>=1.20
Requires-Dist: pandas<2.0,>=1.3
Requires-Dist: python-libsbml~=5.19
Requires-Dist: regex==2022.*
Requires-Dist: requests==2.*
Requires-Dist: tabulate~=0.9
Requires-Dist: xlrd==2.*
Requires-Dist: xlwt~=1.3
Requires-Dist: pytest~=8.3
Requires-Dist: matplotlib==3.*
